Metadata-Version: 2.1
Name: sales_report
Version: 0.1.0
Summary: Пакет для генерации отчётов о продажах из CSV.
Author-email: mikhail <m.zimin@edu.centraluniversity.ru>
Requires-Dist: pandas
